{
  "version": 2,
  "data": {
    "elixir": {
      "version": "v1.18.1",
      "gitref": "refs/tags/v1.18.1",
      "url": "https://github.com/elixir-lang/elixir/releases/tag/v1.18.1"
    },
    "infer-bin": {
      "version": "v1.2.0",
      "gitref": "refs/tags/v1.2.0",
      "url": "https://github.com/facebook/infer/releases/tag/v1.2.0"
    },
    "intel-gmmlib": {
      "version": "22.5.5"
    },
    "intel-media-driver": {
      "version": "24.4.4"
    },
    "jdk17-graalvm-bin": {
      "version": "17.0.12"
    },
    "jdk17-openj9-bin": {
      "version": "jdk-17.0.13+11_openj9-0.48.0",
      "gitref": "refs/tags/jdk-17.0.13+11_openj9-0.48.0",
      "url": "https://github.com/ibmruntimes/semeru17-binaries/releases/tag/jdk-17.0.13%2B11_openj9-0.48.0"
    },
    "jdk21-graalvm-bin": {
      "version": "21.0.4"
    },
    "jdk21-openj9-bin": {
      "version": "jdk-21.0.5+11_openj9-0.48.0",
      "gitref": "refs/tags/jdk-21.0.5+11_openj9-0.48.0",
      "url": "https://github.com/ibmruntimes/semeru21-binaries/releases/tag/jdk-21.0.5%2B11_openj9-0.48.0"
    },
    "lexical-bin": {
      "version": "v0.7.2",
      "gitref": "refs/tags/v0.7.2",
      "url": "https://github.com/lexical-lsp/lexical/releases/tag/v0.7.2"
    },
    "moonlight-qt": {
      "version": "v6.1.0",
      "gitref": "refs/tags/v6.1.0",
      "url": "https://github.com/moonlight-stream/moonlight-qt/releases/tag/v6.1.0"
    },
    "openshift-codeready-bin": {
      "version": "2.45.0"
    },
    "openshift-developer-bin": {
      "version": "v3.16.1"
    },
    "openshift-pipelines-bin": {
      "version": "1.17.0"
    },
    "postman2openapi-bin": {
      "version": "1.2.1",
      "gitref": "refs/tags/1.2.1",
      "url": "https://github.com/kevinswiber/postman2openapi/releases/tag/1.2.1"
    },
    "pragmatapro-fonts": {
      "version": "0.830"
    },
    "pupdate-bin": {
      "version": "4.1.4",
      "gitref": "refs/tags/4.1.4",
      "url": "https://github.com/mattpannella/pupdate/releases/tag/4.1.4"
    },
    "rcu-bin": {
      "version": "d2024.001(q)"
    },
    "rusty-psn-bin": {
      "version": "v0.5.6",
      "gitref": "refs/tags/v0.5.6",
      "url": "https://github.com/RainbowCookie32/rusty-psn/releases/tag/v0.5.6"
    },
    "tidal-dl-ng": {
      "version": "v0.24.6",
      "gitref": "refs/tags/v0.24.6",
      "url": "https://github.com/exislow/tidal-dl-ng/releases/tag/v0.24.6"
    }
  }
}
